text_evaluator/__init__.py
text_evaluator/model.py
text_evaluator/data/data.json
text_evaluator/data/my_model.h5
text_evaluator-0.3.dist-info/METADATA
text_evaluator-0.3.dist-info/WHEEL
text_evaluator-0.3.dist-info/entry_points.txt
text_evaluator-0.3.dist-info/top_level.txt
text_evaluator-0.3.dist-info/RECORD
