Metadata-Version: 2.1
Name: text-evaluator
Version: 0.3
Summary: A text evaluation module using AI-TQA Basic
Home-page: https://github.com/krozen-dev/AI_TextScan
Author: _KroZen_
Author-email: your.email@example.com
Classifier: Programming Language :: Python :: 3
Classifier: License :: OSI Approved :: MIT License
Classifier: Operating System :: OS Independent
Requires-Python: >=3.6
Requires-Dist: tensorflow
Requires-Dist: nltk
